rtlsdr/RTLSDR.py
rtlsdr/__init__.py
rtlsdr/config.json
rtlsdr/const.py
rtlsdr/core.py
rtlsdr/util.py
RTL_SDR-1.0.0.dist-info/METADATA
RTL_SDR-1.0.0.dist-info/WHEEL
RTL_SDR-1.0.0.dist-info/top_level.txt
RTL_SDR-1.0.0.dist-info/RECORD
