Metadata-Version: 2.1
Name: RTL-SDR
Version: 1.0.0
Summary: A wrapper for rtlsdr.dll, which can be used to access RTL2832U by software defined radio programs on Microsoft Windows platform.
Author: Enbuging
Author-email: electricfan@yeah.net
License: MIT
Keywords: radio,SDR,RTL-SDR,RTL2832U,rtlsdr.dll
Platform: Windows
Requires-Dist: numpy >=1.21
